speechify/__init__.py
speechify/api/__init__.py
speechify/api/types/__init__.py
speechify/api/types/audio_stream_request_accept.py
speechify/client.py
speechify/core/__init__.py
speechify/core/api_error.py
speechify/core/client_wrapper.py
speechify/core/datetime_utils.py
speechify/core/file.py
speechify/core/http_client.py
speechify/core/jsonable_encoder.py
speechify/core/pydantic_utilities.py
speechify/core/query_encoder.py
speechify/core/remove_none_from_dict.py
speechify/core/request_options.py
speechify/core/serialization.py
speechify/environment.py
speechify/py.typed
speechify/tts/__init__.py
speechify/tts/audio/__init__.py
speechify/tts/audio/client.py
speechify/tts/audio/types/__init__.py
speechify/tts/audio/types/audio_stream_request_accept.py
speechify/tts/audio/types/get_speech_request_audio_format.py
speechify/tts/audio/types/get_speech_request_model.py
speechify/tts/audio/types/get_stream_request_model.py
speechify/tts/auth/__init__.py
speechify/tts/auth/client.py
speechify/tts/auth/types/__init__.py
speechify/tts/auth/types/create_access_token_request_scope.py
speechify/tts/client.py
speechify/tts/errors/__init__.py
speechify/tts/errors/bad_request_error.py
speechify/tts/errors/forbidden_error.py
speechify/tts/errors/internal_server_error.py
speechify/tts/errors/not_found_error.py
speechify/tts/errors/payment_required_error.py
speechify/tts/errors/unauthorized_error.py
speechify/tts/types/__init__.py
speechify/tts/types/access_token.py
speechify/tts/types/access_token_scope.py
speechify/tts/types/api_key.py
speechify/tts/types/create_voice_language.py
speechify/tts/types/create_voice_model.py
speechify/tts/types/create_voice_model_name.py
speechify/tts/types/created_voice.py
speechify/tts/types/created_voice_gender.py
speechify/tts/types/created_voice_type.py
speechify/tts/types/get_speech_options_request.py
speechify/tts/types/get_speech_response.py
speechify/tts/types/get_speech_response_audio_format.py
speechify_api-1.2.2.dist-info/METADATA
speechify_api-1.2.2.dist-info/WHEEL
speechify_api-1.2.2.dist-info/RECORD
